<?xml version="1.0" encoding="utf-8" ?>
<AnalysisProgramOfRegionAnalysisSessionString xmlns:xsd="http://www.w3.org/2001/XMLSchema" xmlns:xsi="http://www.w3.org/2001/XMLSchema-instance">
  <SaveName>BuildFailureReason/Perl/sjdy521@Mojo-Webqq</SaveName>
  <LearningData>
    <InputPaths>
      <string>Perl/sjdy521@Mojo-Webqq/failed/332708478.log</string>
      <string>Perl/sjdy521@Mojo-Webqq/failed/341246416.log</string>
      <string>Perl/sjdy521@Mojo-Webqq/failed/345524470.log</string>
      <string>Perl/sjdy521@Mojo-Webqq/failed/347585795.log</string>
      <string>Perl/sjdy521@Mojo-Webqq/failed/367594701.log</string>
      <string>Perl/sjdy521@Mojo-Webqq/failed/367594706.log</string>
      <string>Perl/sjdy521@Mojo-Webqq/failed/368688524.log</string>
      <string>Perl/sjdy521@Mojo-Webqq/failed/369927984.log</string>
      <string>Perl/sjdy521@Mojo-Webqq/failed/369957693.log</string>
      <string>Perl/sjdy521@Mojo-Webqq/failed/373752512.log</string>
    </InputPaths>
    <Examples>
      <ExampleDataOfString>
        <InputPath>Perl/sjdy521@Mojo-Webqq/failed/332708478.log</InputPath>
        <Output>t/https.t ........ Connection error: Connect timeout at t/https.t line 17.
# Looks like your test exited with 11 before it could output anything.</Output>
      </ExampleDataOfString>
      <ExampleDataOfString>
        <InputPath>Perl/sjdy521@Mojo-Webqq/failed/341246416.log</InputPath>
        <Output>t/https.t ........ Connection error: Connect timeout at t/https.t line 17.
# Looks like your test exited with 11 before it could output anything.</Output>
      </ExampleDataOfString>
      <ExampleDataOfString>
        <InputPath>Perl/sjdy521@Mojo-Webqq/failed/345524470.log</InputPath>
        <Output>t/https.t ........ Connection error: Connect timeout at t/https.t line 17.
# Looks like your test exited with 11 before it could output anything.</Output>
      </ExampleDataOfString>
      <ExampleDataOfString>
        <InputPath>Perl/sjdy521@Mojo-Webqq/failed/347585795.log</InputPath>
        <Output>t/https.t ........ Connection error: Connect timeout at t/https.t line 17.
# Looks like your test exited with 11 before it could output anything.</Output>
      </ExampleDataOfString>
      <ExampleDataOfString>
        <InputPath>Perl/sjdy521@Mojo-Webqq/failed/367594701.log</InputPath>
        <Output>t/https.t ........ Connection error: Connect timeout at t/https.t line 17.
# Looks like your test exited with 115 before it could output anything.</Output>
      </ExampleDataOfString>
      <ExampleDataOfString>
        <InputPath>Perl/sjdy521@Mojo-Webqq/failed/367594706.log</InputPath>
        <Output>t/https.t ........ Connection error: Connect timeout at t/https.t line 17.
# Looks like your test exited with 115 before it could output anything.</Output>
      </ExampleDataOfString>
      <ExampleDataOfString>
        <InputPath>Perl/sjdy521@Mojo-Webqq/failed/368688524.log</InputPath>
        <Output>t/https.t ........ Connection error: Connect timeout at t/https.t line 17.
# Looks like your test exited with 115 before it could output anything.</Output>
      </ExampleDataOfString>
      <ExampleDataOfString>
        <InputPath>Perl/sjdy521@Mojo-Webqq/failed/369927984.log</InputPath>
        <Output>t/https.t ........ Connection error: Connect timeout at t/https.t line 17.
# Looks like your test exited with 115 before it could output anything.</Output>
      </ExampleDataOfString>
      <ExampleDataOfString>
        <InputPath>Perl/sjdy521@Mojo-Webqq/failed/369957693.log</InputPath>
        <Output>t/https.t ........ Connection error: Connect timeout at t/https.t line 17.
# Looks like your test exited with 115 before it could output anything.</Output>
      </ExampleDataOfString>
      <ExampleDataOfString>
        <InputPath>Perl/sjdy521@Mojo-Webqq/failed/373752512.log</InputPath>
        <Output>t/https.t ........ Connection error: Connect timeout at t/https.t line 17.
# Looks like your test exited with 115 before it could output anything.</Output>
      </ExampleDataOfString>
    </Examples>
  </LearningData>
  <LogKind>
    <Language>java</Language>
    <BuildTool>android</BuildTool>
  </LogKind>
  <Target>BuildFailureReason</Target>
</AnalysisProgramOfRegionAnalysisSessionString>